setup.py
kissanime_dl/__init__.py
kissanime_dl/color_print.py
kissanime_dl/command_line.py
kissanime_dl/js_exc_decode.py
kissanime_dl/jsexec.py
kissanime_dl/kissenc.py
kissanime_dl/openloaddecode.py
kissanime_dl/pkcs7.py
kissanime_dl/session_make.py
kissanime_dl/validhead.py
kissanime_dl/version.py
kissanime_dl/vidextract.py
kissanime_dl.egg-info/PKG-INFO
kissanime_dl.egg-info/SOURCES.txt
kissanime_dl.egg-info/dependency_links.txt
kissanime_dl.egg-info/entry_points.txt
kissanime_dl.egg-info/not-zip-safe
kissanime_dl.egg-info/requires.txt
kissanime_dl.egg-info/top_level.txt