Metadata-Version: 1.0
Name: kissanime-dl
Version: 1.9.4
Summary: Easy downloading .mp4s from kissanime.to
Home-page: https://github.com/wileyyugioh/kissanime_dl
Author: Wiley Y.
Author-email: wileythrowaway001@gmail.com
License: MIT
Platform: UNKNOWN
